Metadata-Version: 2.1
Name: topsis-Bhagesh-101903540
Version: 1.0.0
Summary: It performs topsis for any model
Home-page: https://github.com/bhagesh/topsis-bhagesh-101903540
Author: Bhagesh Gupta
Author-email: bhageshgupta25@gmail.com.com
License: MIT
Platform: UNKNOWN
Classifier: License :: OSI Approved :: MIT License
Classifier: Programming Language :: Python :: 3.6
Classifier: Programming Language :: Python :: 3.7
Classifier: Programming Language :: Python :: 3.8
License-File: LICENSE
